ragna/__init__.py
ragna/__main__.py
ragna/_compat.py
ragna/_docs.py
ragna/_utils.py
ragna/_version.py
ragna/py.typed
ragna/assistants/__init__.py
ragna/assistants/_ai21labs.py
ragna/assistants/_anthropic.py
ragna/assistants/_api.py
ragna/assistants/_cohere.py
ragna/assistants/_demo.py
ragna/assistants/_google.py
ragna/assistants/_openai.py
ragna/core/__init__.py
ragna/core/_components.py
ragna/core/_document.py
ragna/core/_rag.py
ragna/core/_utils.py
ragna/deploy/__init__.py
ragna/deploy/_authentication.py
ragna/deploy/_config.py
ragna/deploy/_api/__init__.py
ragna/deploy/_api/core.py
ragna/deploy/_api/database.py
ragna/deploy/_api/orm.py
ragna/deploy/_api/schemas.py
ragna/deploy/_cli/__init__.py
ragna/deploy/_cli/config.py
ragna/deploy/_cli/core.py
ragna/deploy/_ui/__init__.py
ragna/deploy/_ui/api_wrapper.py
ragna/deploy/_ui/app.py
ragna/deploy/_ui/auth_page.py
ragna/deploy/_ui/central_view.py
ragna/deploy/_ui/js.py
ragna/deploy/_ui/js_utils.py
ragna/deploy/_ui/left_sidebar.py
ragna/deploy/_ui/logout_page.py
ragna/deploy/_ui/main_page.py
ragna/deploy/_ui/modal_configuration.py
ragna/deploy/_ui/modal_welcome.py
ragna/deploy/_ui/right_sidebar.py
ragna/deploy/_ui/styles.py
ragna/deploy/_ui/components/__init__.py
ragna/deploy/_ui/components/file_uploader.py
ragna/deploy/_ui/imgs/chat_bubble.svg
ragna/deploy/_ui/imgs/cloud-upload.svg
ragna/deploy/_ui/imgs/ragna_logo.svg
ragna/deploy/_ui/resources/upload.js
ragna/source_storages/__init__.py
ragna/source_storages/_chroma.py
ragna/source_storages/_demo.py
ragna/source_storages/_lancedb.py
ragna/source_storages/_vector_database.py
Ragna-0.2.1.dist-info/LICENSE
Ragna-0.2.1.dist-info/METADATA
Ragna-0.2.1.dist-info/WHEEL
Ragna-0.2.1.dist-info/entry_points.txt
Ragna-0.2.1.dist-info/top_level.txt
Ragna-0.2.1.dist-info/RECORD
