Metadata-Version: 2.1
Name: Ragna
Version: 0.2.1
Summary: RAG orchestration framework
Author-email: Ragna Development Team <connect@quansight.com>
License: BSD 3-Clause License
Project-URL: Homepage, https://ragna.chat
Project-URL: Documentation, https://ragna.chat
Project-URL: Changelog, https://ragna.chat/en/stable/references/release-notes/
Project-URL: Repository, https://github.com/Quansight/ragna
Classifier: Development Status :: 4 - Beta
Classifier: Programming Language :: Python :: 3.9
Classifier: Programming Language :: Python :: 3.10
Classifier: Programming Language :: Python :: 3.11
Requires-Python: >=3.9
License-File: LICENSE
Requires-Dist: aiofiles
Requires-Dist: emoji
Requires-Dist: fastapi
Requires-Dist: httpx
Requires-Dist: packaging
Requires-Dist: panel ==1.3.8
Requires-Dist: pydantic >=2
Requires-Dist: pydantic-core
Requires-Dist: pydantic-settings >=2
Requires-Dist: PyJWT
Requires-Dist: python-multipart
Requires-Dist: redis
Requires-Dist: questionary
Requires-Dist: rich
Requires-Dist: sqlalchemy >=2
Requires-Dist: starlette
Requires-Dist: tomlkit
Requires-Dist: typer
Requires-Dist: uvicorn
Requires-Dist: importlib-metadata >=4.6 ; python_version < "3.10"
Provides-Extra: all
Requires-Dist: chromadb >=0.4.13 ; extra == 'all'
Requires-Dist: httpx-sse ; extra == 'all'
Requires-Dist: ijson ; extra == 'all'
Requires-Dist: lancedb >=0.2 ; extra == 'all'
Requires-Dist: pyarrow ; extra == 'all'
Requires-Dist: pymupdf >=1.23.6 ; extra == 'all'
Requires-Dist: python-docx ; extra == 'all'
Requires-Dist: python-pptx ; extra == 'all'
Requires-Dist: tiktoken ; extra == 'all'
